epicol18/__init__.py
epicol18/main.py
epicol18/pages/__init__.py
epicol18/pages/diachronic_search.py
epicol18/pages/kwic.py
epicol18/pages/ngrams.py
epicol18/pages/text_search.py
epicol18/pages/topwordspos.py
epicol18-0.1.dist-info/METADATA
epicol18-0.1.dist-info/WHEEL
epicol18-0.1.dist-info/entry_points.txt
epicol18-0.1.dist-info/top_level.txt
epicol18-0.1.dist-info/RECORD
