Metadata-Version: 2.1
Name: epicol18
Version: 0.1
Author: ycvogt
Requires-Dist: altgraph==0.17.4
Requires-Dist: annotated-types==0.7.0
Requires-Dist: auto-py-to-exe==2.46.0
Requires-Dist: beautifulsoup4
Requires-Dist: blinker==1.9.0
Requires-Dist: blis
Requires-Dist: bottle==0.13.2
Requires-Dist: bottle-websocket==0.2.9
Requires-Dist: catalogue==2.0.8
Requires-Dist: certifi==2022.12.7
Requires-Dist: cffi==1.17.1
Requires-Dist: charset-normalizer==3.1.0
Requires-Dist: click==8.1.7
Requires-Dist: cloudpathlib==0.20.0
Requires-Dist: cloudpickle==3.1.1
Requires-Dist: colorama==0.4.6
Requires-Dist: confection==0.0.4
Requires-Dist: curated-tokenizers==0.0.9
Requires-Dist: curated-transformers==0.1.1
Requires-Dist: cymem==2.0.7
Requires-Dist: Cython==0.29.36
Requires-Dist: dash==2.18.2
Requires-Dist: dash-core-components==2.0.0
Requires-Dist: dash-html-components==2.0.0
Requires-Dist: dash-table==5.0.0
Requires-Dist: dash_cytoscape==1.0.2
Requires-Dist: dask
Requires-Dist: Eel==0.18.1
Requires-Dist: filelock==3.16.1
Requires-Dist: Flask==2.2.0
Requires-Dist: fsspec==2024.10.0
Requires-Dist: future==1.0.0
Requires-Dist: gensim==3.0.0
Requires-Dist: gevent==24.11.1
Requires-Dist: gevent-websocket==0.10.1
Requires-Dist: greenlet==3.1.1
Requires-Dist: huggingface-hub==0.26.2
Requires-Dist: idna==3.4
Requires-Dist: importlib_metadata==8.5.0
Requires-Dist: itsdangerous==2.2.0
Requires-Dist: Jinja2==3.1.2
Requires-Dist: langcodes==3.3.0
Requires-Dist: locket==1.0.0
Requires-Dist: markdown-it-py==3.0.0
Requires-Dist: MarkupSafe==2.1.2
Requires-Dist: mdurl==0.1.2
Requires-Dist: mpmath==1.3.0
Requires-Dist: murmurhash==1.0.9
Requires-Dist: nest-asyncio==1.6.0
Requires-Dist: networkx==3.4.2
Requires-Dist: numpy
Requires-Dist: nltk
Requires-Dist: packaging==23.0
Requires-Dist: pandas
Requires-Dist: partd==1.4.2
Requires-Dist: pathy==0.10.1
Requires-Dist: pefile==2023.2.7
Requires-Dist: plotly==5.24.1
Requires-Dist: preshed==3.0.8
Requires-Dist: pyarrow
Requires-Dist: pycparser==2.22
Requires-Dist: pydantic==1.9.2
Requires-Dist: pydantic_core==2.23.4
Requires-Dist: Pygments==2.18.0
Requires-Dist: pyinstaller==6.12.0
Requires-Dist: pyinstaller-hooks-contrib==2025.1
Requires-Dist: pyparsing==3.2.1
Requires-Dist: python-dateutil==2.9.0.post0
Requires-Dist: pytz==2024.2
Requires-Dist: pywin32-ctypes==0.2.3
Requires-Dist: PyYAML==6.0.2
Requires-Dist: regex==2024.11.6
Requires-Dist: requests==2.28.2
Requires-Dist: retrying==1.3.4
Requires-Dist: rich==13.9.4
Requires-Dist: safetensors==0.4.5
Requires-Dist: scipy
Requires-Dist: shellingham==1.5.4
Requires-Dist: six==1.16.0
Requires-Dist: smart-open==6.3.0
Requires-Dist: spacy==3.8.2
Requires-Dist: spacy-curated-transformers==0.3.0
Requires-Dist: spacy-legacy==3.0.12
Requires-Dist: spacy-loggers==1.0.4
Requires-Dist: srsly==2.4.6
Requires-Dist: sympy==1.13.1
Requires-Dist: tenacity==9.0.0
Requires-Dist: thinc
Requires-Dist: tokenizers==0.20.3
Requires-Dist: toolz==1.0.0
Requires-Dist: torch==2.5.1
Requires-Dist: tqdm==4.65.0
Requires-Dist: transformers==4.46.2
Requires-Dist: typer==0.13.1
Requires-Dist: typing_extensions==4.12.2
Requires-Dist: tzdata==2024.2
Requires-Dist: urllib3==1.26.15
Requires-Dist: wasabi==0.10.1
Requires-Dist: weasel==0.4.1
Requires-Dist: Werkzeug==2.2.0
Requires-Dist: wordcloud
Requires-Dist: zipp==3.20.2
Requires-Dist: zope.event==5.0
Requires-Dist: zope.interface==7.2
